lp_rtm.srcs/sources_1/new/top.v
`timescale 1ns / 1ps
//////////////////////////////////////////////////////////////////////////////////
// Module Name: top
// Description: 32-bit Multi-Stage Pipelined Datapath with AES-like
//              Substitution/Permutation Round & DFT Conditional Path.
// IEEE 1364-2001 Verilog Standard Compliant
//////////////////////////////////////////////////////////////////////////////////

module top (
    input  wire        clk,
    input  wire        rst,
    input  wire        enable,
    input  wire        test_mode,
    input  wire [31:0] data_in,
    input  wire [31:0] key_in,
    output reg  [31:0] data_out,
    output reg         corner_case_flag
);

    // Target Test Pattern for DFT / Corner-Case Detection
    localparam [31:0] TEST_PATTERN = 32'hA5A5_5A5A;

    // Pipeline Stage 1 Registers
    reg [31:0] stage1_data;
    reg [31:0] stage1_key;
    reg        stage1_test_mode;
    reg        stage1_pattern_match;

    // Pipeline Stage 2 Registers
    reg [31:0] stage2_data;
    reg        stage2_test_mode;
    reg        stage2_pattern_match;

    // Pipeline Stage 3 Registers
    reg [31:0] stage3_data;
    reg        stage3_test_mode;
    reg        stage3_pattern_match;

    // Intermediate Transformation Signals
    wire [31:0] s1_sub_bytes;
    wire [31:0] s2_shift_rows;
    wire [31:0] s3_mix_columns;

    // =========================================================================
    // Stage 1: Key XOR & Byte-wise Nonlinear Substitution (SubBytes)
    // =========================================================================
    assign s1_sub_bytes[7:0]   = (data_in[7:0]   ^ key_in[7:0])   ^ 8'h63;
    assign s1_sub_bytes[15:8]  = (data_in[15:8]  ^ key_in[15:8])  ^ 8'h7C;
    assign s1_sub_bytes[23:16] = (data_in[23:16] ^ key_in[23:16]) ^ 8'h77;
    assign s1_sub_bytes[31:24] = (data_in[31:24] ^ key_in[31:24]) ^ 8'h7B;

    always @(posedge clk) begin
        if (rst) begin
            stage1_data          <= 32'h0;
            stage1_key           <= 32'h0;
            stage1_test_mode     <= 1'b0;
            stage1_pattern_match <= 1'b0;
        end else if (enable) begin
            stage1_data          <= s1_sub_bytes;
            stage1_key           <= key_in;
            stage1_test_mode     <= test_mode;
            stage1_pattern_match <= (data_in == TEST_PATTERN);
        end
    end

    // =========================================================================
    // Stage 2: Byte Permutation & Rotation (ShiftRows)
    // =========================================================================
    // Circular byte rotation: Byte 0 -> Byte 1 -> Byte 2 -> Byte 3
    assign s2_shift_rows = {stage1_data[23:16], stage1_data[15:8], stage1_data[7:0], stage1_data[31:24]};

    always @(posedge clk) begin
        if (rst) begin
            stage2_data          <= 32'h0;
            stage2_test_mode     <= 1'b0;
            stage2_pattern_match <= 1'b0;
        end else if (enable) begin
            stage2_data          <= s2_shift_rows;
            stage2_test_mode     <= stage1_test_mode;
            stage2_pattern_match <= stage1_pattern_match;
        end
    end

    // =========================================================================
    // Stage 3: Linear Bitwise Combination & Constant XOR (MixColumns)
    // =========================================================================
    assign s3_mix_columns[7:0]   = stage2_data[7:0]   ^ stage2_data[15:8]  ^ 8'h1F;
    assign s3_mix_columns[15:8]  = stage2_data[15:8]  ^ stage2_data[23:16] ^ 8'h3D;
    assign s3_mix_columns[23:16] = stage2_data[23:16] ^ stage2_data[31:24] ^ 8'h5A;
    assign s3_mix_columns[31:24] = stage2_data[31:24] ^ stage2_data[7:0]   ^ 8'h79;

    always @(posedge clk) begin
        if (rst) begin
            stage3_data          <= 32'h0;
            stage3_test_mode     <= 1'b0;
            stage3_pattern_match <= 1'b0;
        end else if (enable) begin
            stage3_data          <= s3_mix_columns;
            stage3_test_mode     <= stage2_test_mode;
            stage3_pattern_match <= stage2_pattern_match;
        end
    end

    // =========================================================================
    // Output Stage: DFT Conditional Path & Data Formatting
    // =========================================================================
    always @(posedge clk) begin
        if (rst) begin
            data_out         <= 32'h0;
            corner_case_flag <= 1'b0;
        end else if (enable) begin
            if (stage3_test_mode && stage3_pattern_match) begin
                // DFT / Corner-case trigger active: Assert flag and invert bit 0 of output
                corner_case_flag <= 1'b1;
                data_out         <= {stage3_data[31:1], ~stage3_data[0]};
            end else begin
                // Normal datapath operation
                corner_case_flag <= 1'b0;
                data_out         <= stage3_data;
            end
        end
    end

endmodule

lp_rtm.srcs/sources_1/new/tb_top.v
`timescale 1ns / 1ps
//////////////////////////////////////////////////////////////////////////////////
// Module Name: tb_top
// Description: Testbench for 32-bit Pipelined Datapath Top Module.
//              - 100 MHz clock generation (10ns period)
//              - Pass 1: 50 random 32-bit inputs with test_mode = 0
//              - Pass 2: Target test vector 32'hA5A5_5A5A with test_mode = 1
//              - VCD trace logging
// IEEE 1364-2001 Verilog Standard Compliant
//////////////////////////////////////////////////////////////////////////////////

module tb_top;

    // Testbench Signals
    reg        clk;
    reg        rst;
    reg        enable;
    reg        test_mode;
    reg [31:0] data_in;
    reg [31:0] key_in;

    wire [31:0] data_out;
    wire        corner_case_flag;

    integer i;

    // Instantiate Unit Under Test (UUT)
    top uut (
        .clk(clk),
        .rst(rst),
        .enable(enable),
        .test_mode(test_mode),
        .data_in(data_in),
        .key_in(key_in),
        .data_out(data_out),
        .corner_case_flag(corner_case_flag)
    );

    // 100 MHz Clock Generation (Period = 10ns)
    initial begin
        clk = 1'b0;
        forever #5 clk = ~clk;
    end

    // VCD Dump Logging
    initial begin
        $dumpfile("sim_output.vcd");
        $dumpvars(0, tb_top);
    end

    // Test Sequence
    initial begin
        // Initialize Inputs
        rst       = 1'b1;
        enable    = 1'b0;
        test_mode = 1'b0;
        data_in   = 32'h0;
        key_in    = 32'h0;

        // Apply Reset Sequence
        #20;
        rst = 1'b0;
        enable = 1'b1;
        #10;

        // ---------------------------------------------------------------------
        // Pass 1: Drive 50 random 32-bit inputs with test_mode = 0
        // ---------------------------------------------------------------------
        $display("=== Starting Pass 1: Normal Operation (test_mode = 0) ===");
        test_mode = 1'b0;
        key_in    = 32'h1234_5678;

        for (i = 0; i < 50; i = i + 1) begin
            data_in = $random;
            @(posedge clk);
            $display("[Pass 1 - Cycle %0d] data_in = 0x%8h | data_out = 0x%8h | corner_case_flag = %b",
                     i, data_in, data_out, corner_case_flag);
        end

        // Drain pipeline stages
        repeat (4) @(posedge clk);

        // ---------------------------------------------------------------------
        // Pass 2: Drive target test vector 32'hA5A5_5A5A with test_mode = 1
        // ---------------------------------------------------------------------
        $display("=== Starting Pass 2: DFT / Test Mode (test_mode = 1) ===");
        test_mode = 1'b1;
        data_in   = 32'hA5A5_5A5A;
        key_in    = 32'h8765_4321;

        @(posedge clk);
        $display("[Pass 2 - Vector Applied] data_in = 0x%8h (test_mode = %b)", data_in, test_mode);

        // Advance clock to trace pipeline propagation (4 pipeline stages)
        repeat (4) begin
            @(posedge clk);
            $display("[Pass 2 - Pipeline Trace] data_out = 0x%8h | corner_case_flag = %b",
                     data_out, corner_case_flag);
        end

        #50;
        $display("=== Simulation Complete ===");
        $finish;
    end

endmodule

reports/sim_output.vcd
$date
   Fri Aug  7 14:23:14 2026
$end
$version
  2020.1
$end
$timescale
  1ps
$end
$scope module tb_top $end
$var reg 1 ! clk $end
$var reg 1 " rst $end
$var reg 1 # enable $end
$var reg 1 $ test_mode $end
$var reg 32 % data_in [31:0] $end
$var reg 32 & key_in [31:0] $end
$var wire 32 ' data_out [31:0] $end
$var wire 1 ( corner_case_flag $end
$var integer 32 ) i $end
$scope module uut $end
$var wire 1 * clk $end
$var wire 1 + rst $end
$var wire 1 , enable $end
$var wire 1 - test_mode $end
$var wire 32 . data_in [31:0] $end
$var wire 32 / key_in [31:0] $end
$var reg 32 0 data_out [31:0] $end
$var reg 1 1 corner_case_flag $end
$var reg 32 2 stage1_data [31:0] $end
$var reg 32 3 stage1_key [31:0] $end
$var reg 1 4 stage1_test_mode $end
$var reg 1 5 stage1_pattern_match $end
$var reg 32 6 stage2_data [31:0] $end
$var reg 1 7 stage2_test_mode $end
$var reg 1 8 stage2_pattern_match $end
$var reg 32 9 stage3_data [31:0] $end
$var reg 1 : stage3_test_mode $end
$var reg 1 ; stage3_pattern_match $end
$var wire 32 < s1_sub_bytes [31:0] $end
$var wire 32 = s2_shift_rows [31:0] $end
$var wire 32 > s3_mix_columns [31:0] $end
$var parameter 32 ? TEST_PATTERN [31:0] $end
$upscope $end
$upscope $end
$enddefinitions $end
#0
$dumpvars
0!
1"
0#
0$
b0 %
b0 &
bx '
x(
bx )
0*
1+
0,
0-
b0 .
b0 /
bx 0
x1
bx 2
bx 3
x4
x5
bx 6
x7
x8
bx 9
x:
x;
b1111011011101110111110001100011 <
bx =
bx >
b10100101101001010101101001011010 ?
$end
#5000
1!
b0 '
0(
1*
b0 0
01
b0 2
b0 3
04
05
b0 6
07
08
b0 9
0:
0;
b0 =
b1111001010110100011110100011111 >
#10000
0!
0*
#15000
1!
1*
#20000
0!
0"
1#
0*
0+
1,
#25000
1!
1*
b1111011011101110111110001100011 2
b1111001010110100011110100011111 9
b1110111011111000110001101111011 =
#30000
0!
b10010000101010011010100100100 %
b10010001101000101011001111000 &
b0 )
0*
b10010000101010011010100100100 .
b10010001101000101011001111000 /
b1111011010101100001111100111111 <
#35000
1!
b11000000100010010101111010000001 %
b1111001010110100011110100011111 '
b1 )
1*
b11000000100010010101111010000001 .
b1111001010110100011110100011111 0
b1111011010101100001111100111111 2
b10010001101000101011001111000 3
b1110111011111000110001101111011 6
b10101001110010100111010010011010 <
b1010110000111110011111101111011 =
b1110101010100010010001000000111 >
#40000
0!
0*
#45000
1!
b10000100100001001101011000001001 %
b10 )
1*
b10000100100001001101011000001001 .
b10101001110010100111010010011010 2
b1010110000111110011111101111011 6
b1110101010100010010001000000111 9
b11101101110001111111110000010010 <
b11001010011101001001101010101001 =
b1010100000100110001110101011011 >
#50000
0!
0*
#55000
1!
b10110001111100000101011001100011 %
b1110101010100010010001000000111 '
b11 )
1*
b10110001111100000101011001100011 .
b1110101010100010010001000000111 0
b11101101110001111111110000010010 2
b11001010011101001001101010101001 6
b1010100000100110001110101011011 9
b11011000101100110111110001111000 <
b11000111111111000001001011101101 =
b11010111001001101001100101100 >
#60000
0!
0*
#65000
1!
b110101110010111101100001101 %
b1010100000100110001110101011011 '
b100 )
1*
b110101110010111101100001101 .
b1010100000100110001110101011011 0
b11011000101100110111110001111000 2
b11000111111111000001001011101101 6
b11010111001001101001100101100 9
b1101111111110100101000100010110 <
b10110011011111000111100011011000 =
b1010011011000011101001111100000 >
#70000
0!
0*
#75000
1!
b1000110110111111001100110001101 %
b11010111001001101001100101100 '
b101 )
1*
b1000110110111111001100110001101 .
b11010111001001101001100101100 0
b1101111111110100101000100010110 2
b10110011011111000111100011011000 6
b1010011011000011101001111100000 9
b101111100111001011001110010110 <
b11111010010100010001011001101111 =
b10010100101010011100110111111 >
#80000
0!
0*
#85000
1!
b10110010110000101000010001100101 %
b1010011011000011101001111100000 '
b110 )
1*
b10110010110000101000010001100101 .
b1010011011000011101001111100000 0
b101111100111001011001110010110 2
b11111010010100010001011001101111 6
b10010100101010011100110111111 9
b11011011100000011010111001111110 <
b10011100101100111001011000101111 =
b11101100111100010111101001100110 >
#90000
0!
0*
#95000
1!
b10001001001101110101001000010010 %
b10010100101010011100110111111 '
b111 )
1*
b10001001001101110101001000010010 .
b10010100101010011100110111111 0
b11011011100000011010111001111110 2
b10011100101100111001011000101111 6
b11101100111100010111101001100110 9
b11100000011101000111100000001001 <
b10000001101011100111111011011011 =
b11001010011101010001100010100110 >
#100000
0!
0*
#105000
1!
b111100111110001100000001 %
b11101100111100010111101001100110 '
b1000 )
1*
b111100111110001100000001 .
b11101100111100010111101001100110 0
b11100000011101000111100000001001 2
b10000001101011100111111011011011 6
b11001010011101010001100010100110 9
b1101001101100001100100100011010 <
b1110100011110000000100111100000 =
b100011011101011110110110111010 >
#110000
0!
0*
#115000
1!
b110110101111100110100001101 %
b11001010011101010001100010100110 '
b1001 )
1*
b110110101111100110100001101 .
b11001010011101010001100010100110 0
b1101001101100001100100100011010 2
b1110100011110000000100111100000 6
b100011011101011110110110111010 9
b1101111100101001110011100010110 <
b10110000110010010001101001101001 =
b11101101010101100100110011110110 >
#120000
0!
0*
#125000
1!
b111011001000111111000101110110 %
b100011011101011110110110111010 '
b1010 )
1*
b111011001000111111000101110110 .
b100011011101011110110110111010 0
b1101111100101001110011100010110 2
b10110000110010010001101001101001 6
b11101101010101100100110011110110 9
b1010010011000001101101101101101 <
b10010100111001110001011001101111 =
b10100000001000111110111001101100 >
#130000
0!
0*
#135000
1!
b11110100011011100110100111101 %
b11101101010101100100110011110110 '
b1011 )
1*
b11110100011011100110100111101 .
b11101101010101100100110011110110 0
b1010010011000001101101101101101 2
b10010100111001110001011001101111 6
b10100000001000111110111001101100 9
b1110111110011101110011100100110 <
b1100000110110110110110101010010 =
b10000010001010011100110001100110 >
#140000
0!
0*
#145000
1!
b1110110110101000101011111101101 %
b10100000001000111110111001101100 '
b1100 )
1*
b1110110110101000101011111101101 .
b10100000001000111110111001101100 0
b1110111110011101110011100100110 2
b1100000110110110110110101010010 6
b10000010001010011100110001100110 9
b11111100101110111110111110110 <
b11001110111001110010011001110111 =
b1001011111000011000101100100000 >
#150000
0!
0*
#155000
1!
b1000110001011011111011110001100 %
b10000010001010011100110001100110 '
b1101 )
1*
b1000110001011011111011110001100 .
b10000010001010011100110001100110 0
b11111100101110111110111110110 2
b11001110111001110010011001110111 6
b1001011111000011000101100100000 9
b101111011011101101110110010111 <
b10010111011111011111011000011111 =
b11000000011100111111110001001110 >
#160000
0!
0*
#165000
1!
b1111100111111011110100111111001 %
b1001011111000011000101100100000 '
b1110 )
1*
b1111100111111011110100111111001 .
b1001011111000011000101100100000 0
b101111011011101101110110010111 2
b10010111011111011111011000011111 6
b11000000011100111111110001001110 9
b10101101111101100001111100010 <
b1101110110111011001011100101111 =
b11110001101100001011011011110110 >
#170000
0!
0*
#175000
1!
b11100011001101110010010011000110 %
b11000000011100111111110001001110 '
b1111 )
1*
b11100011001101110010010011000110 .
b11000000011100111111110001001110 0
b10101101111101100001111100010 2
b1101110110111011001011100101111 6
b11110001101100001011011011110110 9
b10001010011101000000111011011101 <
b10111110110000111110001000010101 =
b111000111010010111011110100111 >
#180000
0!
0*
#185000
1!
b11100010111101111000010011000101 %
b11110001101100001011011011110110 '
b10000 )
1*
b11100010111101111000010011000101 .
b11110001101100001011011011110110 0
b10001010011101000000111011011101 2
b10111110110000111110001000010101 6
b111000111010010111011110100111 9
b10001011101101001010111011011110 <
b1110100000011101101110110001010 =
b11010010001001110001110011101000 >
#190000
0!
0*
#195000
1!
b11010101000100111101001010101010 %
b111000111010010111011110100111 '
b10001 )
1*
b11010101000100111101001010101010 .
b111000111010010111011110100111 0
b10001011101101001010111011011110 2
b1110100000011101101110110001010 6
b11010010001001110001110011101000 9
b10111100010100001111100010110001 <
b10110100101011101101111010001011 =
b10000111001000001110111001001000 >
#200000
0!
0*
#205000
1!
b1110010101011111111011111100101 %
b11010010001001110001110011101000 '
b10010 )
1*
b1110010101011111111011111100101 .
b11010010001001110001110011101000 0
b10111100010100001111100010110001 2
b10110100101011101101111010001011 6
b10000111001000001110111001001000 9
b11011111011001101110111111110 <
b1010000111110001011000110111100 =
b1000110010000000100110101001010 >
#210000
0!
0*
#215000
1!
b10111011110100100111001001110111 %
b10000111001000001110111001001000 '
b10011 )
1*
b10111011110100100111001001110111 .
b10000111001000001110111001001000 0
b11011111011001101110111111110 2
b1010000111110001011000110111100 6
b1000110010000000100110101001010 9
b11010010100100010101100001101100 <
b11101100110111011111111000011011 =
b10010101111100100111010000010010 >
#220000
0!
0*
#225000
1!
b10001001001100101101011000010010 %
b1000110010000000100110101001010 '
b10100 )
1*
b10001001001100101101011000010010 .
b1000110010000000100110101001010 0
b11010010100100010101100001101100 2
b11101100110111011111111000011011 6
b10010101111100100111010000010010 9
b11100000011100011111110000001001 <
b10010001010110000110110011010010 =
b10001110011010110001111011111010 >
#230000
0!
0*
#235000
1!
b1000111111011001101101110001111 %
b10010101111100100111010000010010 '
b10101 )
1*
b1000111111011001101101110001111 .
b10010101111100100111010000010010 0
b11100000011100011111110000001001 2
b10010001010110000110110011010010 6
b10001110011010110001111011111010 9
b101110101011111111000110010100 <
b1110001111111000000100111100000 =
b111010100100110000100110100001 >
#240000
0!
0*
#245000
1!
b1111001001100000110100111110010 %
b10001110011010110001111011111010 '
b10110 )
1*
b1111001001100000110100111110010 .
b10001110011010110001111011111010 0
b101110101011111111000110010100 2
b1110001111111000000100111100000 6
b111010100100110000100110100001 9
b10000011100110100001111101001 <
b10101111111100011001010000101110 =
b11101000110101111100100011110110 >
#250000
0!
0*
#255000
1!
b11100111011101101001011011001110 %
b111010100100110000100110100001 '
b10111 )
1*
b11100111011101101001011011001110 .
b111010100100110000100110100001 0
b10000011100110100001111101001 2
b10101111111100011001010000101110 6
b11101000110101111100100011110110 9
b10001110001101011011110011010101 <
b1110011010000111110100100010000 =
b11111000000001000101100010100101 >
#260000
0!
0*
#265000
1!
b11110100000000000111101011101000 %
b11101000110101111100100011110110 '
b11000 )
1*
b11110100000000000111101011101000 .
b11101000110101111100100011110110 0
b10001110001101011011110011010101 2
b1110011010000111110100100010000 6
b11111000000001000101100010100101 9
b10011101010000110101000011110011 <
b110101101111001101010110001110 =
b11010011010101001011111100110 >
#270000
0!
0*
#275000
1!
b11100010110010100100111011000101 %
b11111000000001000101100010100101 '
b11001 )
1*
b11100010110010100100111011000101 .
b11111000000001000101100010100101 0
b10011101010000110101000011110011 2
b110101101111001101010110001110 6
b11010011010101001011111100110 9
b10001011100010010110010011011110 <
b1000011010100001111001110011101 =
b11000010110100110101010001000100 >
#280000
0!
0*
#285000
1!
b101110010110000100100101011100 %
b11010011010101001011111100110 '
b11010 )
1*
b101110010110000100100101011100 .
b11010011010101001011111100110 0
b10001011100010010110010011011110 2
b1000011010100001111001110011101 6
b11000010110100110101010001000100 9
b1000111000110110110001101000111 <
b10001001011001001101111010001011 =
b10100111010010011001111001110001 >
#290000
0!
0*
#295000
1!
b11011110100011100010100010111101 %
b11000010110100110101010001000100 '
b11011 )
1*
b11011110100011100010100010111101 .
b11000010110100110101010001000100 0
b1000111000110110110001101000111 2
b10001001011001001101111010001011 6
b10100111010010011001111001110001 9
b10110111110011010000001010100110 <
b11011011000110100011101000111 =
b1111011101101111000011101001010 >
#300000
0!
0*
#305000
1!
b10010110101010110101100000101101 %
b10100111010010011001111001110001 '
b11100 )
1*
b10010110101010110101100000101101 .
b10100111010010011001111001110001 0
b10110111110011010000001010100110 2
b11011011000110100011101000111 6
b1111011101101111000011101001010 9
b11111111111010000111001000110110 <
b11001101000000101010011010110111 =
b100101001000100001100100011111 >
#310000
0!
0*
#315000
1!
b10110010101001110010011001100101 %
b1111011101101111000011101001010 '
b11101 )
1*
b10110010101001110010011001100101 .
b1111011101101111000011101001010 0
b11111111111010000111001000110110 2
b11001101000000101010011010110111 6
b100101001000100001100100011111 9
b11011011111001000000110001111110 <
b11101000011100100011011011111111 =
b11100101011001100100001110 >
#320000
0!
0*
#325000
1!
b10110001111011110110001001100011 %
b100101001000100001100100011111 '
b11110 )
1*
b10110001111011110110001001100011 .
b100101001000100001100100011111 0
b11011011111001000000110001111110 2
b11101000011100100011011011111111 6
b11100101011001100100001110 9
b11011000101011000100100001111000 <
b11100100000011000111111011011011 =
b1101110110000000111100111010110 >
#330000
0!
0*
#335000
1!
b101011100111000011100001010 %
b11100101011001100100001110 '
b11111 )
1*
b101011100111000011100001010 .
b11100101011001100100001110 0
b11011000101011000100100001111000 2
b11100100000011000111111011011011 6
b1101110110000000111100111010110 9
b1101100001100001010110100010001 <
b10101100010010000111100011011000 =
b1000110101100100100111110111010 >
#340000
0!
0*
#345000
1!
b11000000001110110010001010000000 %
b1101110110000000111100111010110 '
b100000 )
1*
b11000000001110110010001010000000 .
b1101110110000000111100111010110 0
b1101100001100001010110100010001 2
b10101100010010000111100011011000 6
b1000110101100100100111110111010 9
b10101001011110000000100010011011 <
b110000101011010001000101101100 =
b1101101111100000110110111111 >
#350000
0!
0*
#355000
1!
b10000011001000010000100100000 %
b1000110101100100100111110111010 '
b100001 )
1*
b10000011001000010000100100000 .
b1000110101100100100111110111010 0
b10101001011110000000100010011011 2
b110000101011010001000101101100 6
b1101101111100000110110111111 9
b1111001001001110000101100111011 <
b1111000000010001001101110101001 =
b100101110001111000000101100010 >
#360000
0!
0*
#365000
1!
b1010101011110000100010110101010 %
b1101101111100000110110111111 '
b100010 )
1*
b1010101011110000100010110101010 .
b1101101111100000110110111111 0
b1111001001001110000101100111011 2
b1111000000010001001101110101001 6
b100101110001111000000101100010 9
b111100001110110110111110110001 <
b100111000010110011101101111001 =
b10101000001010101010111000101101 >
#370000
0!
0*
#375000
1!
b11001110110011001100110010011101 %
b100101110001111000000101100010 '
b100011 )
1*
b11001110110011001100110010011101 .
b100101110001111000000101100010 0
b111100001110110110111110110001 2
b100111000010110011101101111001 6
b10101000001010101010111000101101 9
b10100111100011111110011010000110 <
b111011011011111011000100111100 =
b100111011101100000110101011101 >
#380000
0!
0*
#385000
1!
b11001011001000000011111010010110 %
b10101000001010101010111000101101 '
b100100 )
1*
b11001011001000000011111010010110 .
b10101000001010101010111000101101 0
b10100111100011111110011010000110 2
b111011011011111011000100111100 6
b100111011101100000110101011101 9
b10100010011000110001010010001101 <
b10001111111001101000011010100111 =
b1111110000011101110001110010010 >
#390000
0!
0*
#395000
1!
b10001001100000111011100000010011 %
b100111011101100000110101011101 '
b100101 )
1*
b10001001100000111011100000010011 .
b100111011101100000110101011101 0
b10100010011000110001010010001101 2
b10001111111001101000011010100111 6
b1111110000011101110001110010010 9
b11100000110000001001001000001000 <
b1100011000101001000110110100010 =
b1010001001100110101110100111110 >
#400000
0!
0*
#405000
1!
b10000110101111000011100000001101 %
b1111110000011101110001110010010 '
b100110 )
1*
b10000110101111000011100000001101 .
b1111110000011101110001110010010 0
b11100000110000001001001000001000 2
b1100011000101001000110110100010 6
b1010001001100110101110100111110 9
b11101111111111110001001000010110 <
b11000000100100100000100011100000 =
b10111000001011011010010000110000 >
#410000
0!
0*
#415000
1!
b10101001101001111101011001010011 %
b1010001001100110101110100111110 '
b100111 )
1*
b10101001101001111101011001010011 .
b1010001001100110101110100111110 0
b11101111111111110001001000010110 2
b11000000100100100000100011100000 6
b10111000001011011010010000110000 9
b11000000111001001111110001001000 <
b11111111000100100001011011101111 =
b1011001000010001010011111110111 >
#420000
0!
0*
#425000
1!
b110101100111111101110101101011 %
b10111000001011011010010000110000 '
b101000 )
1*
b110101100111111101110101101011 .
b10111000001011011010010000110000 0
b11000000111001001111110001001000 2
b11111111000100100001011011101111 6
b1011001000010001010011111110111 9
b1011100110111001111011101110000 <
b11100100111111000100100011000000 =
b1101001101101110011100111100110 >
#430000
0!
0*
#435000
1!
b11101010101001100010101011010101 %
b1011001000010001010011111110111 '
b101001 )
1*
b11101010101001100010101011010101 .
b1011001000010001010011111110111 0
b1011100110111001111011101110000 2
b11100100111111000100100011000000 6
b1101001101101110011100111100110 9
b10000011111001010000000011001110 <
b11011100111101110111000001011100 =
b1011101010000101000100110010111 >
#440000
0!
0*
#445000
1!
b10000001000101110100101000000010 %
b1101001101101110011100111100110 '
b101010 )
1*
b10000001000101110100101000000010 .
b1101001101101110011100111100110 0
b10000011111001010000000011001110 2
b11011100111101110111000001011100 6
b1011101010000101000100110010111 9
b11101000010101000110000000011001 <
b11100101000000001100111010000011 =
b11111001011100011011101000110011 >
#450000
0!
0*
#455000
1!
b11010111010101100011111010101110 %
b1011101010000101000100110010111 '
b101011 )
1*
b11010111010101100011111010101110 .
b1011101010000101000100110010111 0
b11101000010101000110000000011001 2
b11100101000000001100111010000011 6
b11111001011100011011101000110011 9
b10111110000101010001010010110101 <
b1010100011000000001100111101000 =
b11111101111111111001101010010 >
#460000
0!
0*
#465000
1!
b1110111111111110100100011101 %
b11111001011100011011101000110011 '
b101100 )
1*
b1110111111111110100100011101 .
b11111001011100011011101000110011 0
b10111110000101010001010010110101 2
b1010100011000000001100111101000 6
b11111101111111111001101010010 9
b1100111101111001100001100000110 <
b10101000101001011010110111110 =
b11000101011011100100010011101110 >
#470000
0!
0*
#475000
1!
b11100111110001010111001011001111 %
b11111101111111111001101010010 '
b101101 )
1*
b11100111110001010111001011001111 .
b11111101111111111001101010010 0
b1100111101111001100001100000110 2
b10101000101001011010110111110 6
b11000101011011100100010011101110 9
b10001110100001100101100011010100 <
b10111100110000110000011001100111 =
b11010010010110111001110000010100 >
#480000
0!
0*
#485000
1!
b10001100001000100100100100011 %
b11000101011011100100010011101110 '
b101110 )
1*
b10001100001000100100100100011 .
b11000101011011100100010011101110 0
b10001110100001100101100011010100 2
b10111100110000110000011001100111 6
b11010010010110111001110000010100 9
b1111000110001110110001100111000 <
b10000110010110001101010010001110 =
b10100010001001011111100001111110 >
#490000
0!
0*
#495000
1!
b101000010010110010100001010 %
b11010010010110111001110000010100 '
b101111 )
1*
b101000010010110010100001010 .
b11010010010110111001110000010100 0
b1111000110001110110001100111000 2
b10000110010110001101010010001110 6
b10100010001001011111100001111110 9
b1101100010010100100111100010001 <
b11000111011000110011100001111000 =
b1110001100001001011000101000101 >
#500000
0!
0*
#505000
1!
b11100101011100110000101011001010 %
b10100010001001011111100001111110 '
b110000 )
1*
b11100101011100110000101011001010 .
b10100010001001011111100001111110 0
b1101100010010100100111100010001 2
b11000111011000110011100001111000 6
b1110001100001001011000101000101 9
b10001100001100000010000011010001 <
b1001010010011110001000101101100 =
b11000110111111100110011001011111 >
#510000
0!
0*
#515000
1!
b10011110001100010100110000111100 %
b1110001100001001011000101000101 '
b110001 )
1*
b10011110001100010100110000111100 .
b1110001100001001011000101000101 0
b10001100001100000010000011010001 2
b1001010010011110001000101101100 6
b11000110111111100110011001011111 9
b11110111011100100110011000100111 <
b110000001000001101000110001100 =
b1011111010111110110001101100010 >
#520000
0!
0*
#525000
1!
b11000110111111100110011001011111 '
b110010 )
1*
b11000110111111100110011001011111 0
b11110111011100100110011000100111 2
b110000001000001101000110001100 6
b1011111010111110110001101100010 9
b1110010011001100010011111110111 =
b11000101010010101100110001000010 >
#530000
0!
0*
#535000
1!
b1011111010111110110001101100010 '
1*
b1011111010111110110001101100010 0
b1110010011001100010011111110111 6
b11000101010010101100110001000010 9
b11111100010011100111110011001111 >
#540000
0!
0*
#545000
1!
b11000101010010101100110001000010 '
1*
b11000101010010101100110001000010 0
b11111100010011100111110011001111 9
#550000
0!
0*
#555000
1!
b11111100010011100111110011001111 '
1*
b11111100010011100111110011001111 0
#560000
0!
0*
#565000
1!
1$
b10100101101001010101101001011010 %
b10000111011001010100001100100001 &
1*
1-
b10100101101001010101101001011010 .
b10000111011001010100001100100001 /
b10000111011001010100001100100001 3
14
15
b1011001101101110110010100011000 <
#570000
0!
0*
#575000
1!
1*
b1011001101101110110010100011000 2
17
18
b10110111011001010001100001011001 =
#580000
0!
0*
#585000
1!
1*
b10110111011001010001100001011001 6
1:
1;
b10010111100010000100000001011110 >
#590000
0!
0*
#595000
1!
b11111100010011100111110011001110 '
1(
1*
b11111100010011100111110011001110 0
11
b10010111100010000100000001011110 9
#600000
0!
0*
#605000
1!
b10010111100010000100000001011111 '
1*
b10010111100010000100000001011111 0
